{
  "id": "theory/tls-certificates",
  "title": "TLS i certyfikaty",
  "description": "TLS tworzy szyfrowany kanał między klientem a serwerem za pomocą łańcucha zaufania certyfikatów — błędnie skonfigurowany TLS naraża użytkowników na podsłuch i osłabia bezpieczeństwo wszystkich funkcji zbudowanych na jego podstawie.",
  "source": "@site/i18n/pl/docusaurus-plugin-content-docs/current/theory/07-tls-certificates.md",
  "sourceDirName": "theory",
  "slug": "/theory/tls-certificates",
  "permalink": "/pl/docs/theory/tls-certificates",
  "draft": false,
  "unlisted": false,
  "tags": [
    {
      "inline": true,
      "label": "crypto",
      "permalink": "/pl/docs/tags/crypto"
    },
    {
      "inline": true,
      "label": "tls",
      "permalink": "/pl/docs/tags/tls"
    },
    {
      "inline": true,
      "label": "defense",
      "permalink": "/pl/docs/tags/defense"
    }
  ],
  "version": "current",
  "sidebarPosition": 8,
  "frontMatter": {
    "title": "TLS i certyfikaty",
    "sidebar_position": 8,
    "tags": [
      "crypto",
      "tls",
      "defense"
    ]
  },
  "sidebar": "theorySidebar",
  "previous": {
    "title": "Burp Suite — przechwytywanie HTTP",
    "permalink": "/pl/docs/theory/burp-suite"
  },
  "next": {
    "title": "Cookies i RODO",
    "permalink": "/pl/docs/theory/cookies-gdpr"
  }
}