{
  "id": "theory/http-headers",
  "title": "HTTP Headers & CF-Connecting-IP Spoofing",
  "description": "If a server blindly trusts IP headers like CF-Connecting-IP or X-Forwarded-For without verifying the request actually came through Cloudflare, attackers can spoof any IP address.",
  "source": "@site/docs/theory/11-http-headers.md",
  "sourceDirName": "theory",
  "slug": "/theory/http-headers",
  "permalink": "/docs/theory/http-headers",
  "draft": false,
  "unlisted": false,
  "tags": [
    {
      "inline": true,
      "label": "http",
      "permalink": "/docs/tags/http"
    },
    {
      "inline": true,
      "label": "headers",
      "permalink": "/docs/tags/headers"
    },
    {
      "inline": true,
      "label": "spoofing",
      "permalink": "/docs/tags/spoofing"
    },
    {
      "inline": true,
      "label": "attack",
      "permalink": "/docs/tags/attack"
    }
  ],
  "version": "current",
  "sidebarPosition": 12,
  "frontMatter": {
    "title": "HTTP Headers & CF-Connecting-IP Spoofing",
    "sidebar_position": 12,
    "tags": [
      "http",
      "headers",
      "spoofing",
      "attack"
    ]
  },
  "sidebar": "theorySidebar",
  "previous": {
    "title": "Cryptographic Failures",
    "permalink": "/docs/theory/cryptographic-failures"
  },
  "next": {
    "title": "CSRF — Cross-Site Request Forgery",
    "permalink": "/docs/theory/csrf"
  }
}